dummy_data_generator_id/__init__.py
dummy_data_generator_id/generator.py
dummy_data_generator_id-0.2.3.dist-info/LICENSE
dummy_data_generator_id-0.2.3.dist-info/METADATA
dummy_data_generator_id-0.2.3.dist-info/WHEEL
dummy_data_generator_id-0.2.3.dist-info/top_level.txt
dummy_data_generator_id-0.2.3.dist-info/RECORD
