Metadata-Version: 2.1
Name: dummy-data-generator-id
Version: 0.2.3
Summary: A library for generating realistic dummy data for Indonesian context
Home-page: https://github.com/bri-anadi/dummy-data-generator-id
Author: Brian Adi
Author-email: uix.brianadi@gmail.com
License: UNKNOWN
Keywords: dummy-data generator indonesia random
Platform: UNKNOWN
Classifier: Development Status :: 3 - Alpha
Classifier: Intended Audience :: Developers
Classifier: License :: OSI Approved :: MIT License
Classifier: Operating System :: OS Independent
Classifier: Programming Language :: Python :: 3
Classifier: Programming Language :: Python :: 3.7
Classifier: Programming Language :: Python :: 3.8
Classifier: Programming Language :: Python :: 3.9
Classifier: Programming Language :: Python :: 3.10
Requires-Python: >=3.7
Requires-Dist: uuid
